{"files":{"apps/mobile/.next/react-loadable-manifest.json":{"size":230,"mtime_nanos":1774875316022165717,"mode":420,"is_dir":false},"apps/mobile/.next/cache/webpack/server-production":{"size":0,"mtime_nanos":0,"mode":0,"is_dir":true},"apps/mobile/.next/cache/swc/plugins/macos_aarch64_24.0.0":{"size":0,"mtime_nanos":0,"mode":0,"is_dir":true},"apps/mobile/.next/build-manifest.json":{"size":509,"mtime_nanos":1774875316022166842,"mode":420,"is_dir":false},"apps/mobile/.next/server/app/_global-error.segments/_global-error":{"size":0,"mtime_nanos":0,"mode":0,"is_dir":true},"apps/mobile/.next/server/app/_not-found.rsc":{"size":3872,"mtime_nanos":1774875317730915310,"mode":420,"is_dir":false},"apps/mobile/.next/cache/.rscinfo":{"size":102,"mtime_nanos":1774875108655593278,"mode":420,"is_dir":false},"apps/mobile/.next/server/app/page_client-reference-manifest.js":{"size":7238,"mtime_nanos":1774875316025000200,"mode":420,"is_dir":false},"apps/mobile/.next/static/chunks/app/_global-error/page-144cdafd0a31c8b3.js":{"size":150,"mtime_nanos":1774875316023159976,"mode":420,"is_dir":false},"apps/mobile/.next":{"size":0,"mtime_nanos":0,"mode":0,"is_dir":true},"apps/mobile/.next/images-manifest.json":{"size":1193,"mtime_nanos":1774875317962834739,"mode":420,"is_dir":false},"apps/mobile/.next/required-server-files.js":{"size":9473,"mtime_nanos":1774875317218370229,"mode":420,"is_dir":false},"apps/mobile/.next/routes-manifest.json":{"size":1902,"mtime_nanos":1774875317930542828,"mode":420,"is_dir":false},"apps/mobile/.next/server/app/page.js":{"size":27274,"mtime_nanos":1774875315054254936,"mode":420,"is_dir":false},"apps/mobile/.next/server/chunks/263.js":{"size":365538,"mtime_nanos":1774875315054192643,"mode":420,"is_dir":false},"apps/mobile/.next/server/pages":{"size":0,"mtime_nanos":0,"mode":0,"is_dir":true},"apps/mobile/.next/static/chunks/app/_not-found/page-8398617f082361d6.js":{"size":2666,"mtime_nanos":1774875316023139100,"mode":420,"is_dir":false},"apps/mobile/.next/cache/webpack/server-production/2.pack":{"size":1321275,"mtime_nanos":1774875240091985021,"mode":420,"is_dir":false},"apps/mobile/.next/export-marker.json":{"size":111,"mtime_nanos":1774875317973029954,"mode":420,"is_dir":false},"apps/mobile/.next/server/app/favicon.ico.body":{"size":25931,"mtime_nanos":1774875317726143476,"mode":420,"is_dir":false},"apps/mobile/.next/server/app/manifest.webmanifest/route_client-reference-manifest.js":{"size":368,"mtime_nanos":1774875316024877658,"mode":420,"is_dir":false},"apps/mobile/.next/static/chunks/547f2400.8952c5bbbc7f3042.js":{"size":77200,"mtime_nanos":1774875316023379852,"mode":420,"is_dir":false},"apps/mobile/.next/server/app/manifest.webmanifest/route.js":{"size":11642,"mtime_nanos":1774875315054616522,"mode":420,"is_dir":false},"apps/mobile/.next/static/chunks/next":{"size":0,"mtime_nanos":0,"mode":0,"is_dir":true},"apps/mobile/.next/server/app/index.rsc":{"size":3703,"mtime_nanos":1774875317731173854,"mode":420,"is_dir":false},"apps/mobile/.next/static/chunks/next/dist/client":{"size":0,"mtime_nanos":0,"mode":0,"is_dir":true},"apps/mobile/.next/server/app/index.segments/_tree.segment.rsc":{"size":444,"mtime_nanos":1774875317730765559,"mode":420,"is_dir":false},"apps/mobile/.next/static/chunks/next/dist/client/components/builtin/not-found-144cdafd0a31c8b3.js":{"size":150,"mtime_nanos":1774875316024738281,"mode":420,"is_dir":false},"apps/mobile/.next/static/chunks/webpack-330f359d757fac05.js":{"size":3447,"mtime_nanos":1774875316023112225,"mode":420,"is_dir":false},"apps/mobile/.next/cache/.previewinfo":{"size":262,"mtime_nanos":1774875108658469971,"mode":420,"is_dir":false},"apps/mobile/.next/server/app/manifest.webmanifest.body":{"size":289,"mtime_nanos":1774875317726199560,"mode":420,"is_dir":false},"apps/mobile/.next/server/app/_not-found.html":{"size":7109,"mtime_nanos":1774875317730929268,"mode":420,"is_dir":false},"apps/mobile/.next/static/media/4cf2300e9c8272f7-s.p.woff2":{"size":28388,"mtime_nanos":1774875316022630346,"mode":420,"is_dir":false},"apps/mobile/.next/static/media/747892c23ea88013-s.woff2":{"size":13036,"mtime_nanos":1774875316022589346,"mode":420,"is_dir":false},"apps/mobile/.next/static/9dzMnnMuQlFEOMMzpLD0h/_buildManifest.js":{"size":515,"mtime_nanos":1774875316022665596,"mode":420,"is_dir":false},"apps/mobile/.next/server/app/_not-found.segments/_head.segment.rsc":{"size":978,"mtime_nanos":1774875317730734475,"mode":420,"is_dir":false},"apps/mobile/.next/server/interception-route-rewrite-manifest.js":{"size":48,"mtime_nanos":1774875315148021308,"mode":420,"is_dir":false},"apps/mobile/.next/cache/webpack/client-production":{"size":0,"mtime_nanos":0,"mode":0,"is_dir":true},"apps/mobile/.next/cache/swc":{"size":0,"mtime_nanos":0,"mode":0,"is_dir":true},"apps/mobile/.next/server/prefetch-hints.json":{"size":2,"mtime_nanos":1774875317946846056,"mode":420,"is_dir":false},"apps/mobile/.next/cache/webpack/client-production/3.pack":{"size":2370081,"mtime_nanos":1774875316071634030,"mode":420,"is_dir":false},"apps/mobile/.next/types/routes.d.ts":{"size":1397,"mtime_nanos":1774875314425555742,"mode":420,"is_dir":false},"apps/mobile/.next/server/app/_global-error/page_client-reference-manifest.js":{"size":7325,"mtime_nanos":1774875316024868366,"mode":420,"is_dir":false},"apps/mobile/.next/cache/webpack/client-production/4.pack":{"size":275835,"mtime_nanos":1774875316071484070,"mode":420,"is_dir":false},"apps/mobile/.next/cache/webpack/edge-server-production/index.pack.old":{"size":165642,"mtime_nanos":1774875132673232591,"mode":420,"is_dir":false},"apps/mobile/.next/server/app/_not-found.segments/_not-found/__PAGE__.segment.rsc":{"size":1382,"mtime_nanos":1774875317731446523,"mode":420,"is_dir":false},"apps/mobile/.next/server/app/_global-error.segments/_head.segment.rsc":{"size":579,"mtime_nanos":1774875317730690266,"mode":420,"is_dir":false},"apps/mobile/.next/server/app/_not-found.segments/_tree.segment.rsc":{"size":518,"mtime_nanos":1774875317730656974,"mode":420,"is_dir":false},"apps/mobile/.next/cache/webpack/server-production/1.pack":{"size":18503,"mtime_nanos":1774875315119542764,"mode":420,"is_dir":false},"apps/mobile/.next/BUILD_ID":{"size":21,"mtime_nanos":1774875317370166115,"mode":420,"is_dir":false},"apps/mobile/.next/static/chunks/polyfills-42372ed130431b0a.js":{"size":112594,"mtime_nanos":1774875316022611596,"mode":420,"is_dir":false},"apps/mobile/.next/server/app/_not-found/page_client-reference-manifest.js":{"size":7319,"mtime_nanos":1774875316024873199,"mode":420,"is_dir":false},"apps/mobile/.next/static/chunks/app/page-424b530753fed3e0.js":{"size":3355,"mtime_nanos":1774875316023065600,"mode":420,"is_dir":false},"apps/mobile/.next/static/chunks/next/dist/client/components/builtin/unauthorized-144cdafd0a31c8b3.js":{"size":150,"mtime_nanos":1774875316024754531,"mode":420,"is_dir":false},"apps/mobile/.next/server/app-paths-manifest.json":{"size":252,"mtime_nanos":1774875315133592305,"mode":420,"is_dir":false},"apps/mobile/.next/static/media":{"size":0,"mtime_nanos":0,"mode":0,"is_dir":true},"apps/mobile/.next/server/app/_not-found/page.js":{"size":23532,"mtime_nanos":1774875315054541605,"mode":420,"is_dir":false},"apps/mobile/.next/server/app/_not-found.segments/_not-found.segment.rsc":{"size":271,"mtime_nanos":1774875317730773059,"mode":420,"is_dir":false},"apps/mobile/.next/server/app/favicon.ico/route.js":{"size":41818,"mtime_nanos":1774875315054619231,"mode":420,"is_dir":false},"apps/mobile/.next/server/app/page.js.nft.json":{"size":17289,"mtime_nanos":1774875320258139736,"mode":420,"is_dir":false},"apps/mobile/.next/server/next-font-manifest.json":{"size":219,"mtime_nanos":1774875316022250384,"mode":420,"is_dir":false},"apps/mobile/.next/server/webpack-runtime.js":{"size":1438,"mtime_nanos":1774875315054265102,"mode":420,"is_dir":false},"apps/mobile/.next/static/media/8d697b304b401681-s.woff2":{"size":14676,"mtime_nanos":1774875316022610137,"mode":420,"is_dir":false},"apps/mobile/.next/cache/webpack/client-production/index.pack":{"size":10262654,"mtime_nanos":1774875316072616122,"mode":420,"is_dir":false},"apps/mobile/.next/server/app/_global-error.segments/_full.segment.rsc":{"size":4792,"mtime_nanos":1774875317730564140,"mode":420,"is_dir":false},"apps/mobile/.next/static/chunks/next/dist/client/components/builtin/forbidden-144cdafd0a31c8b3.js":{"size":150,"mtime_nanos":1774875316024733573,"mode":420,"is_dir":false},"apps/mobile/.next/server/chunks/404.js":{"size":31478,"mtime_nanos":1774875315054184268,"mode":420,"is_dir":false},"apps/mobile/.next/static/chunks/next/dist":{"size":0,"mtime_nanos":0,"mode":0,"is_dir":true},"apps/mobile/.next/cache/webpack/server-production/4.pack":{"size":5733887,"mtime_nanos":1774875315119508139,"mode":420,"is_dir":false},"apps/mobile/.next/static/9dzMnnMuQlFEOMMzpLD0h/_ssgManifest.js":{"size":80,"mtime_nanos":1774875317952975777,"mode":420,"is_dir":false},"apps/mobile/.next/server/app/_not-found.segments/_full.segment.rsc":{"size":3872,"mtime_nanos":1774875317730805726,"mode":420,"is_dir":false},"apps/mobile/.next/server/app/_not-found.segments/_index.segment.rsc":{"size":604,"mtime_nanos":1774875317730715225,"mode":420,"is_dir":false},"apps/mobile/.next/static/media/93f479601ee12b01-s.p.woff2":{"size":31288,"mtime_nanos":1774875316022682221,"mode":420,"is_dir":false},"apps/mobile/.turbo/turbo-build.log":{"size":3680,"mtime_nanos":1774875320294574558,"mode":420,"is_dir":false},"apps/mobile/.next/server/app/_not-found.segments/_not-found":{"size":0,"mtime_nanos":0,"mode":0,"is_dir":true},"apps/mobile/.next/diagnostics/build-diagnostics.json":{"size":94,"mtime_nanos":1774875317373715646,"mode":420,"is_dir":false},"apps/mobile/.next/cache/webpack/edge-server-production/0.pack":{"size":276,"mtime_nanos":1774875216146985352,"mode":420,"is_dir":false},"apps/mobile/.next/cache/webpack/edge-server-production/index.pack":{"size":1451278,"mtime_nanos":1774875216147119936,"mode":420,"is_dir":false},"apps/mobile/.next/server/app/favicon.ico/route.js.nft.json":{"size":16600,"mtime_nanos":1774875320257693315,"mode":420,"is_dir":false},"apps/mobile/.next/server/middleware-build-manifest.js":{"size":448,"mtime_nanos":1774875316022220926,"mode":420,"is_dir":false},"apps/mobile/.next/next-server.js.nft.json":{"size":105771,"mtime_nanos":1774875320272489988,"mode":420,"is_dir":false},"apps/mobile/.next/static/chunks/framework-a358b1f51e337541.js":{"size":189678,"mtime_nanos":1774875316023387561,"mode":420,"is_dir":false},"apps/mobile/.next/static/chunks/main-app-3fd5912e959d8442.js":{"size":521,"mtime_nanos":1774875316022891682,"mode":420,"is_dir":false},"apps/mobile/.next/server/app/_not-found":{"size":0,"mtime_nanos":0,"mode":0,"is_dir":true},"apps/mobile/.next/server/app/_global-error.segments/_global-error/__PAGE__.segment.rsc":{"size":3337,"mtime_nanos":1774875317731439356,"mode":420,"is_dir":false},"apps/mobile/.next/diagnostics/framework.json":{"size":37,"mtime_nanos":1774875314447482603,"mode":420,"is_dir":false},"apps/mobile/.next/trace-build":{"size":1201,"mtime_nanos":1774875320274018876,"mode":420,"is_dir":false},"apps/mobile/.next/types/app/layout.ts":{"size":3898,"mtime_nanos":1774875315054833482,"mode":420,"is_dir":false},"apps/mobile/.next/app-path-routes-manifest.json":{"size":196,"mtime_nanos":1774875317218919317,"mode":420,"is_dir":false},"apps/mobile/.next/static/media/9610d9e46709d722-s.woff2":{"size":12608,"mtime_nanos":1774875316022680680,"mode":420,"is_dir":false},"apps/mobile/.next/server/chunks/375.js":{"size":152542,"mtime_nanos":1774875315054175310,"mode":420,"is_dir":false},"apps/mobile/.next/static/chunks/app":{"size":0,"mtime_nanos":0,"mode":0,"is_dir":true},"apps/mobile/.next/static/chunks/app/manifest.webmanifest":{"size":0,"mtime_nanos":0,"mode":0,"is_dir":true},"apps/mobile/.next/server/app/index.segments/__PAGE__.segment.rsc":{"size":590,"mtime_nanos":1774875317730812226,"mode":420,"is_dir":false},"apps/mobile/.next/prerender-manifest.json":{"size":3972,"mtime_nanos":1774875317939502991,"mode":420,"is_dir":false},"apps/mobile/.next/server/app/_global-error/page.js.nft.json":{"size":17591,"mtime_nanos":1774875320258191486,"mode":420,"is_dir":false},"apps/mobile/.next/static/chunks/298.d7876efd5a94f0b7.js":{"size":34020,"mtime_nanos":1774875316023137725,"mode":420,"is_dir":false},"apps/mobile/.next/server/app/_global-error.segments/_index.segment.rsc":{"size":271,"mtime_nanos":1774875317730653933,"mode":420,"is_dir":false},"apps/mobile/.next/server/app/_global-error.meta":{"size":350,"mtime_nanos":1774875317730839268,"mode":420,"is_dir":false},"apps/mobile/.next/server/functions-config-manifest.json":{"size":37,"mtime_nanos":1774875317367260547,"mode":420,"is_dir":false},"apps/mobile/.next/server/chunks/940.js":{"size":27001,"mtime_nanos":1774875315054236644,"mode":420,"is_dir":false},"apps/mobile/.next/cache/webpack/client-production/1.pack":{"size":673771,"mtime_nanos":1774875316071491946,"mode":420,"is_dir":false},"apps/mobile/.next/static/chunks/90-dca1434e6ab84f9d.js":{"size":227813,"mtime_nanos":1774875316023647480,"mode":420,"is_dir":false},"apps/mobile/.next/static/chunks/628c8b96-cdfc45e32fce7014.js":{"size":199863,"mtime_nanos":1774875316023422311,"mode":420,"is_dir":false},"apps/mobile/.next/static/chunks/next/dist/client/components/builtin/app-error-144cdafd0a31c8b3.js":{"size":150,"mtime_nanos":1774875316024760073,"mode":420,"is_dir":false},"apps/mobile/.next/types":{"size":0,"mtime_nanos":0,"mode":0,"is_dir":true},"apps/mobile/.next/server/server-reference-manifest.js":{"size":123,"mtime_nanos":1774875315054847149,"mode":420,"is_dir":false},"apps/mobile/.next/static":{"size":0,"mtime_nanos":0,"mode":0,"is_dir":true},"apps/mobile/.next/diagnostics":{"size":0,"mtime_nanos":0,"mode":0,"is_dir":true},"apps/mobile/.next/types/validator.ts":{"size":2111,"mtime_nanos":1774875314425839786,"mode":420,"is_dir":false},"apps/mobile/.next/cache/webpack/server-production/3.pack":{"size":7922847,"mtime_nanos":1774875315119502014,"mode":420,"is_dir":false},"apps/mobile/.next/server/app/_global-error/page.js":{"size":27579,"mtime_nanos":1774875315054608939,"mode":420,"is_dir":false},"apps/mobile/.next/static/css/5a8c61ea997dac71.css":{"size":39194,"mtime_nanos":1774875316023200226,"mode":420,"is_dir":false},"apps/mobile/.next/server/app/index.segments/_head.segment.rsc":{"size":927,"mtime_nanos":1774875317730810601,"mode":420,"is_dir":false},"apps/mobile/.next/required-server-files.json":{"size":9444,"mtime_nanos":1774875317218149602,"mode":420,"is_dir":false},"apps/mobile/.next/server/pages/404.html":{"size":7109,"mtime_nanos":1774875317790775174,"mode":420,"is_dir":false},"apps/mobile/.next/types/app/page.ts":{"size":3886,"mtime_nanos":1774875315054811649,"mode":420,"is_dir":false},"apps/mobile/.next/server/app/_global-error.rsc":{"size":4792,"mtime_nanos":1774875317730838143,"mode":420,"is_dir":false},"apps/mobile/.next/server/app/manifest.webmanifest":{"size":0,"mtime_nanos":0,"mode":0,"is_dir":true},"apps/mobile/.next/server":{"size":0,"mtime_nanos":0,"mode":0,"is_dir":true},"apps/mobile/.next/server/app/_global-error.html":{"size":9025,"mtime_nanos":1774875317730914560,"mode":420,"is_dir":false},"apps/mobile/.next/next-minimal-server.js.nft.json":{"size":15751,"mtime_nanos":1774875320272516405,"mode":420,"is_dir":false},"apps/mobile/.next/server/app/_global-error":{"size":0,"mtime_nanos":0,"mode":0,"is_dir":true},"apps/mobile/.next/server/pages/500.html":{"size":9025,"mtime_nanos":1774875317800801012,"mode":420,"is_dir":false},"apps/mobile/.next/server/app/index.segments/_index.segment.rsc":{"size":1698,"mtime_nanos":1774875317730819059,"mode":420,"is_dir":false},"apps/mobile/.next/cache/webpack/server-production/index.pack":{"size":11989943,"mtime_nanos":1774875315120079352,"mode":420,"is_dir":false},"apps/mobile/.next/server/app":{"size":0,"mtime_nanos":0,"mode":0,"is_dir":true},"apps/mobile/.next/server/app/_global-error.segments/_global-error.segment.rsc":{"size":271,"mtime_nanos":1774875317730619099,"mode":420,"is_dir":false},"apps/mobile/.next/server/app/_not-found/page.js.nft.json":{"size":17613,"mtime_nanos":1774875320258130527,"mode":420,"is_dir":false},"apps/mobile/.next/cache/webpack/client-production/0.pack":{"size":46633434,"mtime_nanos":1774875316076898952,"mode":420,"is_dir":false},"apps/mobile/.next/server/app/index.segments/_full.segment.rsc":{"size":3703,"mtime_nanos":1774875317730799976,"mode":420,"is_dir":false},"apps/mobile/.next/server/app/manifest.webmanifest.meta":{"size":251,"mtime_nanos":1774875317726198602,"mode":420,"is_dir":false},"apps/mobile/.next/server/pages-manifest.json":{"size":58,"mtime_nanos":1774875317914862106,"mode":420,"is_dir":false},"apps/mobile/.next/server/server-reference-manifest.json":{"size":84,"mtime_nanos":1774875315054846316,"mode":420,"is_dir":false},"apps/mobile/.next/static/chunks/app/layout-15b9d21f1c8f9004.js":{"size":585,"mtime_nanos":1774875316022991391,"mode":420,"is_dir":false},"apps/mobile/.next/server/app/_global-error.segments/_tree.segment.rsc":{"size":266,"mtime_nanos":1774875317730562974,"mode":420,"is_dir":false},"apps/mobile/.next/static/media/ba015fad6dcf6784-s.woff2":{"size":15292,"mtime_nanos":1774875316022594929,"mode":420,"is_dir":false},"apps/mobile/.next/static/chunks/next/dist/client/components":{"size":0,"mtime_nanos":0,"mode":0,"is_dir":true},"apps/mobile/.next/cache/webpack/client-production/index.pack.old":{"size":10116795,"mtime_nanos":1774875240928987059,"mode":420,"is_dir":false},"apps/mobile/.next/cache":{"size":0,"mtime_nanos":0,"mode":0,"is_dir":true},"apps/mobile/.next/static/css":{"size":0,"mtime_nanos":0,"mode":0,"is_dir":true},"apps/mobile/.next/cache/swc/plugins":{"size":0,"mtime_nanos":0,"mode":0,"is_dir":true},"apps/mobile/.next/cache/webpack/server-production/5.pack":{"size":6270949,"mtime_nanos":1774875315119604139,"mode":420,"is_dir":false},"apps/mobile/.next/server/app/index.html":{"size":6154,"mtime_nanos":1774875317731169895,"mode":420,"is_dir":false},"apps/mobile/.next/static/chunks/next/dist/client/components/builtin":{"size":0,"mtime_nanos":0,"mode":0,"is_dir":true},"apps/mobile/.next/cache/webpack/server-production/index.pack.old":{"size":11858557,"mtime_nanos":1774875298965398600,"mode":420,"is_dir":false},"apps/mobile/.next/server/app/manifest.webmanifest/route.js.nft.json":{"size":16637,"mtime_nanos":1774875320258210778,"mode":420,"is_dir":false},"apps/mobile/.next/server/middleware-manifest.json":{"size":83,"mtime_nanos":1774875315148021558,"mode":420,"is_dir":false},"apps/mobile/.next/server/app/_not-found.segments":{"size":0,"mtime_nanos":0,"mode":0,"is_dir":true},"apps/mobile/.next/server/next-font-manifest.js":{"size":248,"mtime_nanos":1774875316022227259,"mode":420,"is_dir":false},"apps/mobile/.next/cache/webpack/edge-server-production":{"size":0,"mtime_nanos":0,"mode":0,"is_dir":true},"apps/mobile/.next/types/app":{"size":0,"mtime_nanos":0,"mode":0,"is_dir":true},"apps/mobile/.next/cache/.tsbuildinfo":{"size":375051,"mtime_nanos":1774875316858769377,"mode":420,"is_dir":false},"apps/mobile/.next/server/app/_global-error.segments":{"size":0,"mtime_nanos":0,"mode":0,"is_dir":true},"apps/mobile/.next/server/chunks":{"size":0,"mtime_nanos":0,"mode":0,"is_dir":true},"apps/mobile/.next/static/chunks/main-6d67cd427d1cc7b0.js":{"size":143143,"mtime_nanos":1774875316022907140,"mode":420,"is_dir":false},"apps/mobile/.next/server/app/index.meta":{"size":255,"mtime_nanos":1774875317731177271,"mode":420,"is_dir":false},"apps/mobile/.next/static/9dzMnnMuQlFEOMMzpLD0h":{"size":0,"mtime_nanos":0,"mode":0,"is_dir":true},"apps/mobile/.next/static/chunks/709.f64c85035ca3499d.js":{"size":194676,"mtime_nanos":1774875316023547354,"mode":420,"is_dir":false},"apps/mobile/.next/static/chunks/app/_not-found":{"size":0,"mtime_nanos":0,"mode":0,"is_dir":true},"apps/mobile/.next/server/app/_not-found.meta":{"size":335,"mtime_nanos":1774875317730954435,"mode":420,"is_dir":false},"apps/mobile/.next/server/app/favicon.ico.meta":{"size":211,"mtime_nanos":1774875317726197852,"mode":420,"is_dir":false},"apps/mobile/.next/cache/webpack/client-production/2.pack":{"size":311483,"mtime_nanos":1774875316071459237,"mode":420,"is_dir":false},"apps/mobile/.next/server/app/index.segments":{"size":0,"mtime_nanos":0,"mode":0,"is_dir":true},"apps/mobile/.next/static/chunks/next/dist/client/components/builtin/global-error-cd839afe1a04a584.js":{"size":178,"mtime_nanos":1774875316024886741,"mode":420,"is_dir":false},"apps/mobile/.next/server/middleware-react-loadable-manifest.js":{"size":218,"mtime_nanos":1774875316022196217,"mode":420,"is_dir":false},"apps/mobile/.next/trace":{"size":45920,"mtime_nanos":1774875320273823125,"mode":420,"is_dir":false},"apps/mobile/.next/types/package.json":{"size":18,"mtime_nanos":1774875315054831774,"mode":420,"is_dir":false},"apps/mobile/.next/static/chunks":{"size":0,"mtime_nanos":0,"mode":0,"is_dir":true},"apps/mobile/.next/static/chunks/app/manifest.webmanifest/route-144cdafd0a31c8b3.js":{"size":150,"mtime_nanos":1774875316023198976,"mode":420,"is_dir":false},"apps/mobile/.next/cache/webpack/server-production/0.pack":{"size":18677979,"mtime_nanos":1774875298959481297,"mode":420,"is_dir":false},"apps/mobile/.next/server/app/favicon.ico":{"size":0,"mtime_nanos":0,"mode":0,"is_dir":true},"apps/mobile/.next/static/chunks/app/_global-error":{"size":0,"mtime_nanos":0,"mode":0,"is_dir":true},"apps/mobile/.next/package.json":{"size":20,"mtime_nanos":1774875314431881381,"mode":420,"is_dir":false},"apps/mobile/.next/cache/webpack":{"size":0,"mtime_nanos":0,"mode":0,"is_dir":true}},"order":["apps/mobile/.next","apps/mobile/.next/BUILD_ID","apps/mobile/.next/app-path-routes-manifest.json","apps/mobile/.next/build-manifest.json","apps/mobile/.next/cache","apps/mobile/.next/cache/.previewinfo","apps/mobile/.next/cache/.rscinfo","apps/mobile/.next/cache/.tsbuildinfo","apps/mobile/.next/cache/swc","apps/mobile/.next/cache/swc/plugins","apps/mobile/.next/cache/swc/plugins/macos_aarch64_24.0.0","apps/mobile/.next/cache/webpack","apps/mobile/.next/cache/webpack/client-production","apps/mobile/.next/cache/webpack/client-production/0.pack","apps/mobile/.next/cache/webpack/client-production/1.pack","apps/mobile/.next/cache/webpack/client-production/2.pack","apps/mobile/.next/cache/webpack/client-production/3.pack","apps/mobile/.next/cache/webpack/client-production/4.pack","apps/mobile/.next/cache/webpack/client-production/index.pack","apps/mobile/.next/cache/webpack/client-production/index.pack.old","apps/mobile/.next/cache/webpack/edge-server-production","apps/mobile/.next/cache/webpack/edge-server-production/0.pack","apps/mobile/.next/cache/webpack/edge-server-production/index.pack","apps/mobile/.next/cache/webpack/edge-server-production/index.pack.old","apps/mobile/.next/cache/webpack/server-production","apps/mobile/.next/cache/webpack/server-production/0.pack","apps/mobile/.next/cache/webpack/server-production/1.pack","apps/mobile/.next/cache/webpack/server-production/2.pack","apps/mobile/.next/cache/webpack/server-production/3.pack","apps/mobile/.next/cache/webpack/server-production/4.pack","apps/mobile/.next/cache/webpack/server-production/5.pack","apps/mobile/.next/cache/webpack/server-production/index.pack","apps/mobile/.next/cache/webpack/server-production/index.pack.old","apps/mobile/.next/diagnostics","apps/mobile/.next/diagnostics/build-diagnostics.json","apps/mobile/.next/diagnostics/framework.json","apps/mobile/.next/export-marker.json","apps/mobile/.next/images-manifest.json","apps/mobile/.next/next-minimal-server.js.nft.json","apps/mobile/.next/next-server.js.nft.json","apps/mobile/.next/package.json","apps/mobile/.next/prerender-manifest.json","apps/mobile/.next/react-loadable-manifest.json","apps/mobile/.next/required-server-files.js","apps/mobile/.next/required-server-files.json","apps/mobile/.next/routes-manifest.json","apps/mobile/.next/server","apps/mobile/.next/server/app","apps/mobile/.next/server/app/_global-error","apps/mobile/.next/server/app/_global-error/page.js","apps/mobile/.next/server/app/_global-error/page.js.nft.json","apps/mobile/.next/server/app/_global-error/page_client-reference-manifest.js","apps/mobile/.next/server/app/_global-error.html","apps/mobile/.next/server/app/_global-error.meta","apps/mobile/.next/server/app/_global-error.rsc","apps/mobile/.next/server/app/_global-error.segments","apps/mobile/.next/server/app/_global-error.segments/_full.segment.rsc","apps/mobile/.next/server/app/_global-error.segments/_global-error","apps/mobile/.next/server/app/_global-error.segments/_global-error/__PAGE__.segment.rsc","apps/mobile/.next/server/app/_global-error.segments/_global-error.segment.rsc","apps/mobile/.next/server/app/_global-error.segments/_head.segment.rsc","apps/mobile/.next/server/app/_global-error.segments/_index.segment.rsc","apps/mobile/.next/server/app/_global-error.segments/_tree.segment.rsc","apps/mobile/.next/server/app/_not-found","apps/mobile/.next/server/app/_not-found/page.js","apps/mobile/.next/server/app/_not-found/page.js.nft.json","apps/mobile/.next/server/app/_not-found/page_client-reference-manifest.js","apps/mobile/.next/server/app/_not-found.html","apps/mobile/.next/server/app/_not-found.meta","apps/mobile/.next/server/app/_not-found.rsc","apps/mobile/.next/server/app/_not-found.segments","apps/mobile/.next/server/app/_not-found.segments/_full.segment.rsc","apps/mobile/.next/server/app/_not-found.segments/_head.segment.rsc","apps/mobile/.next/server/app/_not-found.segments/_index.segment.rsc","apps/mobile/.next/server/app/_not-found.segments/_not-found","apps/mobile/.next/server/app/_not-found.segments/_not-found/__PAGE__.segment.rsc","apps/mobile/.next/server/app/_not-found.segments/_not-found.segment.rsc","apps/mobile/.next/server/app/_not-found.segments/_tree.segment.rsc","apps/mobile/.next/server/app/favicon.ico","apps/mobile/.next/server/app/favicon.ico/route.js","apps/mobile/.next/server/app/favicon.ico/route.js.nft.json","apps/mobile/.next/server/app/favicon.ico.body","apps/mobile/.next/server/app/favicon.ico.meta","apps/mobile/.next/server/app/index.html","apps/mobile/.next/server/app/index.meta","apps/mobile/.next/server/app/index.rsc","apps/mobile/.next/server/app/index.segments","apps/mobile/.next/server/app/index.segments/__PAGE__.segment.rsc","apps/mobile/.next/server/app/index.segments/_full.segment.rsc","apps/mobile/.next/server/app/index.segments/_head.segment.rsc","apps/mobile/.next/server/app/index.segments/_index.segment.rsc","apps/mobile/.next/server/app/index.segments/_tree.segment.rsc","apps/mobile/.next/server/app/manifest.webmanifest","apps/mobile/.next/server/app/manifest.webmanifest/route.js","apps/mobile/.next/server/app/manifest.webmanifest/route.js.nft.json","apps/mobile/.next/server/app/manifest.webmanifest/route_client-reference-manifest.js","apps/mobile/.next/server/app/manifest.webmanifest.body","apps/mobile/.next/server/app/manifest.webmanifest.meta","apps/mobile/.next/server/app/page.js","apps/mobile/.next/server/app/page.js.nft.json","apps/mobile/.next/server/app/page_client-reference-manifest.js","apps/mobile/.next/server/app-paths-manifest.json","apps/mobile/.next/server/chunks","apps/mobile/.next/server/chunks/263.js","apps/mobile/.next/server/chunks/375.js","apps/mobile/.next/server/chunks/404.js","apps/mobile/.next/server/chunks/940.js","apps/mobile/.next/server/functions-config-manifest.json","apps/mobile/.next/server/interception-route-rewrite-manifest.js","apps/mobile/.next/server/middleware-build-manifest.js","apps/mobile/.next/server/middleware-manifest.json","apps/mobile/.next/server/middleware-react-loadable-manifest.js","apps/mobile/.next/server/next-font-manifest.js","apps/mobile/.next/server/next-font-manifest.json","apps/mobile/.next/server/pages","apps/mobile/.next/server/pages/404.html","apps/mobile/.next/server/pages/500.html","apps/mobile/.next/server/pages-manifest.json","apps/mobile/.next/server/prefetch-hints.json","apps/mobile/.next/server/server-reference-manifest.js","apps/mobile/.next/server/server-reference-manifest.json","apps/mobile/.next/server/webpack-runtime.js","apps/mobile/.next/static","apps/mobile/.next/static/9dzMnnMuQlFEOMMzpLD0h","apps/mobile/.next/static/9dzMnnMuQlFEOMMzpLD0h/_buildManifest.js","apps/mobile/.next/static/9dzMnnMuQlFEOMMzpLD0h/_ssgManifest.js","apps/mobile/.next/static/chunks","apps/mobile/.next/static/chunks/298.d7876efd5a94f0b7.js","apps/mobile/.next/static/chunks/547f2400.8952c5bbbc7f3042.js","apps/mobile/.next/static/chunks/628c8b96-cdfc45e32fce7014.js","apps/mobile/.next/static/chunks/709.f64c85035ca3499d.js","apps/mobile/.next/static/chunks/90-dca1434e6ab84f9d.js","apps/mobile/.next/static/chunks/app","apps/mobile/.next/static/chunks/app/_global-error","apps/mobile/.next/static/chunks/app/_global-error/page-144cdafd0a31c8b3.js","apps/mobile/.next/static/chunks/app/_not-found","apps/mobile/.next/static/chunks/app/_not-found/page-8398617f082361d6.js","apps/mobile/.next/static/chunks/app/layout-15b9d21f1c8f9004.js","apps/mobile/.next/static/chunks/app/manifest.webmanifest","apps/mobile/.next/static/chunks/app/manifest.webmanifest/route-144cdafd0a31c8b3.js","apps/mobile/.next/static/chunks/app/page-424b530753fed3e0.js","apps/mobile/.next/static/chunks/framework-a358b1f51e337541.js","apps/mobile/.next/static/chunks/main-6d67cd427d1cc7b0.js","apps/mobile/.next/static/chunks/main-app-3fd5912e959d8442.js","apps/mobile/.next/static/chunks/next","apps/mobile/.next/static/chunks/next/dist","apps/mobile/.next/static/chunks/next/dist/client","apps/mobile/.next/static/chunks/next/dist/client/components","apps/mobile/.next/static/chunks/next/dist/client/components/builtin","apps/mobile/.next/static/chunks/next/dist/client/components/builtin/app-error-144cdafd0a31c8b3.js","apps/mobile/.next/static/chunks/next/dist/client/components/builtin/forbidden-144cdafd0a31c8b3.js","apps/mobile/.next/static/chunks/next/dist/client/components/builtin/global-error-cd839afe1a04a584.js","apps/mobile/.next/static/chunks/next/dist/client/components/builtin/not-found-144cdafd0a31c8b3.js","apps/mobile/.next/static/chunks/next/dist/client/components/builtin/unauthorized-144cdafd0a31c8b3.js","apps/mobile/.next/static/chunks/polyfills-42372ed130431b0a.js","apps/mobile/.next/static/chunks/webpack-330f359d757fac05.js","apps/mobile/.next/static/css","apps/mobile/.next/static/css/5a8c61ea997dac71.css","apps/mobile/.next/static/media","apps/mobile/.next/static/media/4cf2300e9c8272f7-s.p.woff2","apps/mobile/.next/static/media/747892c23ea88013-s.woff2","apps/mobile/.next/static/media/8d697b304b401681-s.woff2","apps/mobile/.next/static/media/93f479601ee12b01-s.p.woff2","apps/mobile/.next/static/media/9610d9e46709d722-s.woff2","apps/mobile/.next/static/media/ba015fad6dcf6784-s.woff2","apps/mobile/.next/trace","apps/mobile/.next/trace-build","apps/mobile/.next/types","apps/mobile/.next/types/app","apps/mobile/.next/types/app/layout.ts","apps/mobile/.next/types/app/page.ts","apps/mobile/.next/types/package.json","apps/mobile/.next/types/routes.d.ts","apps/mobile/.next/types/validator.ts","apps/mobile/.turbo/turbo-build.log"]}